{
  "miniapp": {
    "version": "1",
    "name": "Hot Potato",
                    "iconUrl": "https://hotpotato-blond.vercel.app/icon.svg",
                "homeUrl": "https://hotpotato-blond.vercel.app",
                "splashImageUrl": "https://hotpotato-blond.vercel.app/splash.svg",
    "splashBackgroundColor": "#FF6B00",
    "subtitle": "Steal the potato, grow the pot",
    "description": "A fun game where players pay to steal a virtual potato. The pot grows with each steal until it pops, awarding the last holder!",
    "primaryCategory": "games",
    "tags": ["game", "potato", "steal", "base", "ethereum"],
    "requiredChains": [
      "eip155:8453"
    ],
    "requiredCapabilities": [
      "actions.signIn",
      "wallet.getEthereumProvider",
      "actions.share"
    ],
                    "screenshotUrls": [
                  "https://hotpotato-blond.vercel.app/screenshot1.svg",
                  "https://hotpotato-blond.vercel.app/screenshot2.svg",
                  "https://hotpotato-blond.vercel.app/screenshot3.svg"
                ],
                "heroImageUrl": "https://hotpotato-blond.vercel.app/hero.svg",
    "tagline": "Steal the potato, win the pot!",
    "ogTitle": "Hot Potato Game",
    "ogDescription": "Steal the potato and grow the pot! A fun blockchain game on Base.",
                    "ogImageUrl": "https://hotpotato-blond.vercel.app/og-image.svg"
  }
}
